wrts/Session.py
wrts/__init__.py
wrts/enums.py
wrts/exceptions.py
wrts/types/List.py
wrts/types/Notif.py
wrts/types/Question.py
wrts/types/Subject.py
wrts/types/User.py
wrts-0.7.0.dist-info/LICENSE
wrts-0.7.0.dist-info/METADATA
wrts-0.7.0.dist-info/WHEEL
wrts-0.7.0.dist-info/entry_points.txt
wrts-0.7.0.dist-info/RECORD
