Metadata-Version: 2.1
Name: wrts
Version: 0.7.0
Summary: A small lil library for using the WRTS API 
Author: BadPythonCoder
Author-email: xsare435@gmail.com
Requires-Python: >=3.10,<4.0
Classifier: Programming Language :: Python :: 3
Classifier: Programming Language :: Python :: 3.10
Classifier: Programming Language :: Python :: 3.11
Classifier: Programming Language :: Python :: 3.12
Classifier: Programming Language :: Python :: 3.13
Requires-Dist: requests (>=2.31.0,<3.0.0)
